[
  {
    "serviceType": "airport-shuttle",
    "pickupAddress": "\u30aa\u30fc\u30af\u30e9\u30f3\u30c9\u7a7a\u6e2f",
    "pickupAddresses": [],
    "dropoffAddress": "\u30af\u30a4\u30fc\u30f3\u30b9\u30c8\u30ea\u30fc\u30c8\u3001\u30aa\u30fc\u30af\u30e9\u30f3\u30c9CBD",
    "date": "2025-12-25",
    "time": "16:00",
    "passengers": "3",
    "departureFlightNumber": "",
    "departureTime": "",
    "arrivalFlightNumber": "",
    "arrivalTime": "",
    "name": "\u6700\u7d42\u30c6\u30b9\u30c8\u30e6\u30fc\u30b6\u30fc\u65e5\u672c\u8a9e",
    "email": "final-ja@bookaride.co.nz",
    "phone": "+64211111113",
    "notes": "",
    "pricing": {
      "totalPrice": 125.0
    },
    "status": "pending",
    "payment_status": "unpaid",
    "createdAt": "2025-12-07T09:16:11.237000",
    "id": "ad8413d0-2ba7-4791-a516-1d62d139a05a",
    "referenceNumber": 30
  },
  {
    "serviceType": "airport-shuttle",
    "pickupAddress": "\u5965\u514b\u5170\u673a\u573a",
    "pickupAddresses": [],
    "dropoffAddress": "\u7687\u540e\u8857\uff0c\u5965\u514b\u5170\u5e02\u4e2d\u5fc3",
    "date": "2025-12-25",
    "time": "14:00",
    "passengers": "1",
    "departureFlightNumber": "",
    "departureTime": "",
    "arrivalFlightNumber": "",
    "arrivalTime": "",
    "name": "\u6700\u7ec8\u6d4b\u8bd5\u7528\u6237\u4e2d\u6587",
    "email": "final-zh@bookaride.co.nz",
    "phone": "+64211111112",
    "notes": "",
    "pricing": {
      "totalPrice": 100.0
    },
    "status": "pending",
    "payment_status": "unpaid",
    "createdAt": "2025-12-07T09:16:11.228000",
    "id": "b5d2eb61-4959-4c71-89e3-f302755e968a",
    "referenceNumber": 29
  },
  {
    "serviceType": "airport-shuttle",
    "pickupAddress": "492 Hillsborough Road, Mount Roskill, Auckland 1041, New Zealand",
    "pickupAddresses": [],
    "dropoffAddress": "67 Gifford Avenue, Wesley, Auckland 1041, New Zealand",
    "date": "2025-12-06",
    "time": "21:25",
    "passengers": "1",
    "departureFlightNumber": "",
    "departureTime": "",
    "arrivalFlightNumber": "",
    "arrivalTime": "",
    "name": "Craig Canty",
    "email": "ccantynz@gmail.com",
    "phone": "+6421339030",
    "notes": "",
    "pricing": {
      "distance": 4.54,
      "basePrice": 11.35,
      "airportFee": 0,
      "oversizedLuggageFee": 0,
      "passengerFee": 0,
      "totalPrice": 100,
      "calculating": false
    },
    "status": "confirmed",
    "payment_status": "paid",
    "createdAt": "2025-12-05T03:25:26.320000",
    "id": "fd73a543-5b79-4322-934a-45a5dcd36637",
    "referenceNumber": 18
  },
  {
    "serviceType": "private-transfer",
    "pickupAddress": "492 Hillsborough Rd, Mount Roskill",
    "pickupAddresses": [],
    "dropoffAddress": "83 Alec Craig Way, Gulf Harbour, Whangapar\u0101oa 0930, New Zealand",
    "date": "2025-12-06",
    "time": "18:35",
    "passengers": "1",
    "departureFlightNumber": "",
    "departureTime": "",
    "arrivalFlightNumber": "",
    "arrivalTime": "",
    "name": "Craig Canty",
    "email": "ccantynz@gmail.com",
    "phone": "+6421339030",
    "notes": "",
    "pricing": {
      "distance": 62.67,
      "basePrice": 156.68,
      "airportFee": 0,
      "passengerFee": 0,
      "totalPrice": 156.68,
      "calculating": false
    },
    "status": "confirmed",
    "payment_status": "pending",
    "createdAt": "2025-12-03T17:36:40.698000",
    "id": "948eef76-98b7-4b04-82d6-2d13510d5bb8",
    "referenceNumber": 16
  },
  {
    "serviceType": "private-transfer",
    "pickupAddress": "492 Hillsborough Rd, Mount Roskill",
    "pickupAddresses": [],
    "dropoffAddress": "83 Alec Craig Way, Gulf Harbour, Whangapar\u0101oa 0930, New Zealand",
    "date": "2025-12-06",
    "time": "18:35",
    "passengers": "1",
    "departureFlightNumber": "",
    "departureTime": "",
    "arrivalFlightNumber": "",
    "arrivalTime": "",
    "name": "Craig Canty",
    "email": "ccantynz@gmail.com",
    "phone": "+6421339030",
    "notes": "",
    "pricing": {
      "distance": 62.67,
      "basePrice": 156.68,
      "airportFee": 0,
      "passengerFee": 0,
      "totalPrice": 156.68,
      "calculating": false
    },
    "status": "pending",
    "payment_status": "pending",
    "createdAt": "2025-12-03T17:35:44.917000",
    "id": "a3d9c899-5deb-4491-983d-ec19532c426f",
    "referenceNumber": 15
  },
  {
    "serviceType": "airport-shuttle",
    "pickupAddress": "83 Alec Craig Way, Gulf Harbour, Whangapar\u0101oa 0930, New Zealand",
    "pickupAddresses": [],
    "dropoffAddress": "Domestic Terminal, Auckland 2022, New Zealand",
    "date": "2025-12-27",
    "time": "18:33",
    "passengers": "1",
    "departureFlightNumber": "",
    "departureTime": "",
    "arrivalFlightNumber": "",
    "arrivalTime": "",
    "name": "Craig Canty",
    "email": "ccantynz@gmail.com",
    "phone": "+6421339030",
    "notes": "",
    "pricing": {
      "distance": 77.05,
      "basePrice": 192.62,
      "airportFee": 0,
      "passengerFee": 0,
      "totalPrice": 192.62,
      "calculating": false
    },
    "status": "pending",
    "payment_status": "pending",
    "createdAt": "2025-12-03T17:33:56.093000",
    "id": "e77d073f-41fc-41b1-9eb7-7453d950078f",
    "referenceNumber": 14
  },
  {
    "serviceType": "airport-shuttle",
    "pickupAddress": "83 Alec Craig Way, Gulf Harbour, Whangapar\u0101oa 0930, New Zealand",
    "pickupAddresses": [],
    "dropoffAddress": "Domestic Terminal, Auckland 2022, New Zealand",
    "date": "2025-12-12",
    "time": "13:16",
    "passengers": "1",
    "departureFlightNumber": "",
    "departureTime": "",
    "arrivalFlightNumber": "",
    "arrivalTime": "",
    "name": "Craig Canty",
    "email": "ccantynz@gmail.com",
    "phone": "+6421339030",
    "notes": "",
    "pricing": {
      "distance": 77.05,
      "basePrice": 192.62,
      "airportFee": 0,
      "passengerFee": 0,
      "totalPrice": 192.62,
      "calculating": false
    },
    "status": "pending",
    "payment_status": "pending",
    "createdAt": "2025-12-03T12:16:44.094000",
    "id": "6333be29-ec6b-49f9-a844-0e6b32e886e4",
    "referenceNumber": 13
  },
  {
    "serviceType": "private-transfer",
    "pickupAddress": "492 Hillsborough Road, Mount Roskill, Auckland 1041, New Zealand",
    "pickupAddresses": [],
    "dropoffAddress": "67 Gifford Avenue, Wesley, Auckland 1041, New Zealand",
    "date": "2025-12-12",
    "time": "00:42",
    "passengers": "1",
    "departureFlightNumber": "",
    "departureTime": "",
    "arrivalFlightNumber": "",
    "arrivalTime": "",
    "name": "Craig Canty",
    "email": "ccantynz@gmail.com",
    "phone": "+6421339030",
    "notes": "",
    "pricing": {
      "distance": 4.54,
      "basePrice": 11.35,
      "airportFee": 0,
      "passengerFee": 0,
      "totalPrice": 11.35,
      "calculating": false
    },
    "status": "confirmed",
    "payment_status": "paid",
    "createdAt": "2025-12-03T11:43:57.231000",
    "id": "164f47bc-5659-4432-a408-f9bb7ed0dc66",
    "referenceNumber": 12
  },
  {
    "serviceType": "private-transfer",
    "pickupAddress": "492 Hillsborough Road, Mount Roskill, Auckland 1041, New Zealand",
    "pickupAddresses": [],
    "dropoffAddress": "496 Hillsborough Road, Mount Roskill, Auckland 1041, New Zealand",
    "date": "2025-12-12",
    "time": "00:42",
    "passengers": "1",
    "departureFlightNumber": "",
    "departureTime": "",
    "arrivalFlightNumber": "",
    "arrivalTime": "",
    "name": "Craig Canty",
    "email": "ccantynz@gmail.com",
    "phone": "+6421339030",
    "notes": "",
    "pricing": {
      "distance": 0.06,
      "basePrice": 0.15,
      "airportFee": 0,
      "passengerFee": 0,
      "totalPrice": 0.15,
      "calculating": false
    },
    "status": "pending",
    "payment_status": "unpaid",
    "createdAt": "2025-12-03T11:43:29.217000",
    "id": "7b08513a-3fbb-4d1a-8a69-88a44ac9da3d",
    "referenceNumber": 11
  },
  {
    "serviceType": "private-transfer",
    "pickupAddress": "492 Hillsborough Road, Mount Roskill, Auckland 1041, New Zealand",
    "pickupAddresses": [],
    "dropoffAddress": "496 Hillsborough Road, Mount Roskill, Auckland 1041, New Zealand",
    "date": "2025-12-12",
    "time": "00:42",
    "passengers": "1",
    "departureFlightNumber": "",
    "departureTime": "",
    "arrivalFlightNumber": "",
    "arrivalTime": "",
    "name": "Craig Canty",
    "email": "ccantynz@gmail.com",
    "phone": "+6421339030",
    "notes": "",
    "pricing": {
      "distance": 0.06,
      "basePrice": 0.15,
      "airportFee": 0,
      "passengerFee": 0,
      "totalPrice": 0.15,
      "calculating": false
    },
    "status": "pending",
    "payment_status": "unpaid",
    "createdAt": "2025-12-03T11:43:19.318000",
    "id": "690a1fa1-a3c4-43a2-bbc0-d8d1d66a534d",
    "referenceNumber": 10
  },
  {
    "serviceType": "private-transfer",
    "pickupAddress": "492 Hillsborough Road, Mount Roskill, Auckland 1041, New Zealand",
    "pickupAddresses": [],
    "dropoffAddress": "496 Hillsborough Road, Mount Roskill, Auckland 1041, New Zealand",
    "date": "2025-12-12",
    "time": "00:42",
    "passengers": "1",
    "departureFlightNumber": "",
    "departureTime": "",
    "arrivalFlightNumber": "",
    "arrivalTime": "",
    "name": "Craig Canty",
    "email": "ccantynz@gmail.com",
    "phone": "+6421339030",
    "notes": "",
    "pricing": {
      "distance": 0.06,
      "basePrice": 0.15,
      "airportFee": 0,
      "passengerFee": 0,
      "totalPrice": 0.15,
      "calculating": false
    },
    "status": "pending",
    "payment_status": "unpaid",
    "createdAt": "2025-12-03T11:42:38.805000",
    "id": "e4391a97-9373-476c-97c8-c78f346e243d",
    "referenceNumber": 9
  },
  {
    "serviceType": "private-transfer",
    "pickupAddress": "83 Alec Craig Way, Gulf Harbour, Whangapar\u0101oa 0930, New Zealand",
    "pickupAddresses": [],
    "dropoffAddress": "Domestic Terminal, Auckland 2022, New Zealand",
    "date": "2025-12-12",
    "time": "12:40",
    "passengers": "1",
    "departureFlightNumber": "",
    "departureTime": "",
    "arrivalFlightNumber": "",
    "arrivalTime": "",
    "name": "Craig Canty",
    "email": "ccantynz@gmail.com",
    "phone": "+6421339030",
    "notes": "",
    "pricing": {
      "distance": 77.05,
      "basePrice": 192.62,
      "airportFee": 0,
      "passengerFee": 0,
      "totalPrice": 192.62,
      "calculating": false
    },
    "status": "pending",
    "payment_status": "pending",
    "createdAt": "2025-12-03T11:40:24.830000",
    "id": "b0a511c4-45ba-48c2-a0b4-628cc93fb672",
    "referenceNumber": 8
  },
  {
    "serviceType": "airport-shuttle",
    "pickupAddress": "83 Alec Craig Way, Gulf Harbour, Whangapar\u0101oa 0930, New Zealand",
    "pickupAddresses": [],
    "dropoffAddress": "Domestic Terminal, Auckland 2022, New Zealand",
    "date": "2025-12-11",
    "time": "12:17",
    "passengers": "1",
    "departureFlightNumber": "",
    "departureTime": "",
    "arrivalFlightNumber": "",
    "arrivalTime": "",
    "name": "Craig Canty",
    "email": "ccantynz@gmail.com",
    "phone": "+6421339030",
    "notes": "",
    "pricing": {
      "distance": 77.05,
      "basePrice": 192.62,
      "airportFee": 0,
      "passengerFee": 0,
      "totalPrice": 192.62,
      "calculating": false
    },
    "status": "pending",
    "payment_status": "unpaid",
    "createdAt": "2025-12-03T11:18:10.093000",
    "id": "844b46d1-52b8-4603-a551-d209fe1922de",
    "referenceNumber": 6
  },
  {
    "serviceType": "airport-shuttle",
    "pickupAddress": "83 Alec Craig Way, Gulf Harbour, Whangapar\u0101oa 0930, New Zealand",
    "pickupAddresses": [],
    "dropoffAddress": "Domestic Terminal, Auckland 2022, New Zealand",
    "date": "2025-12-11",
    "time": "12:17",
    "passengers": "1",
    "departureFlightNumber": "",
    "departureTime": "",
    "arrivalFlightNumber": "",
    "arrivalTime": "",
    "name": "Craig Canty",
    "email": "ccantynz@gmail.com",
    "phone": "+6421339030",
    "notes": "",
    "pricing": {
      "distance": 77.05,
      "basePrice": 192.62,
      "airportFee": 0,
      "passengerFee": 0,
      "totalPrice": 192.62,
      "calculating": false
    },
    "status": "pending",
    "payment_status": "unpaid",
    "createdAt": "2025-12-03T11:17:42.521000",
    "id": "a2143d56-a711-44cd-a9ce-5613935b020f",
    "referenceNumber": 5
  },
  {
    "serviceType": "airport-shuttle",
    "pickupAddress": "83 Alec Craig Way, Gulf Harbour, Whangapar\u0101oa 0930, New Zealand",
    "pickupAddresses": [],
    "dropoffAddress": "International Terminal, Auckland 2022, New Zealand",
    "date": "2025-12-12",
    "time": "12:04",
    "passengers": "1",
    "departureFlightNumber": "",
    "departureTime": "",
    "arrivalFlightNumber": "",
    "arrivalTime": "",
    "name": "Craig Canty",
    "email": "ccantynz@gmail.com",
    "phone": "+6421339030",
    "notes": "",
    "pricing": {
      "distance": 76.82,
      "basePrice": 192.05,
      "airportFee": 0,
      "passengerFee": 0,
      "totalPrice": 192.05,
      "calculating": false
    },
    "status": "pending",
    "payment_status": "unpaid",
    "createdAt": "2025-12-03T11:04:59.406000",
    "id": "5ea50f72-38c4-45fb-a9ce-15d408e718ea",
    "referenceNumber": 4
  },
  {
    "serviceType": "private-auckland",
    "pickupAddress": "Whangarei, Marina",
    "pickupAddresses": [],
    "dropoffAddress": "auckland domestic",
    "date": "2025-12-05",
    "time": "22:34",
    "passengers": "1",
    "departureFlightNumber": "",
    "departureTime": "",
    "arrivalFlightNumber": "",
    "arrivalTime": "",
    "name": "Craig Canty",
    "email": "ccantynz@gmail.com",
    "phone": "+6421339030",
    "notes": "",
    "pricing": {
      "distance": 25,
      "basePrice": 62.5,
      "airportFee": 0,
      "passengerFee": 0,
      "totalPrice": 62.5,
      "calculating": false
    },
    "status": "pending",
    "payment_status": "unpaid",
    "createdAt": "2025-12-03T09:35:41.789000",
    "id": "2ce62aaa-8764-4739-9b2d-acb67e3a79ca",
    "referenceNumber": 2
  },
  {
    "serviceType": "auckland-airport",
    "pickupAddress": "83 Alec Craig way",
    "pickupAddresses": [],
    "dropoffAddress": "international airport",
    "date": "2025-12-05",
    "time": "17:25",
    "passengers": "6",
    "departureFlightNumber": "",
    "departureTime": "",
    "arrivalFlightNumber": "",
    "arrivalTime": "",
    "name": "Craig Canty",
    "email": "ccantynz@gmail.com",
    "phone": "+6421339030",
    "notes": "",
    "pricing": {
      "distance": 25,
      "basePrice": 62.5,
      "airportFee": 25,
      "passengerFee": 25,
      "totalPrice": 112.5,
      "calculating": false
    },
    "status": "pending",
    "payment_status": "unpaid",
    "createdAt": "2025-12-03T09:29:00.240000",
    "id": "2f1ee585-8158-4d1f-9d5f-9583f12019ef",
    "referenceNumber": 1
  },
  {
    "serviceType": "airport-shuttle",
    "pickupAddress": "Auckland Airport Domestic",
    "pickupAddresses": [],
    "dropoffAddress": "24 Harvest Ave Orewa",
    "date": "2025-12-24",
    "time": "11:30",
    "passengers": "2",
    "departureFlightNumber": "",
    "departureTime": "",
    "arrivalFlightNumber": "NZ580",
    "arrivalTime": "11:15",
    "name": "JEANETTE GOWAN DAVIES",
    "email": "jeanette.davies49@gmail.com",
    "phone": "+64222013326",
    "notes": "",
    "pricing": {
      "distance": 62.07,
      "basePrice": 155.18,
      "airportFee": 0,
      "oversizedLuggageFee": 0,
      "passengerFee": 5,
      "totalPrice": 160.18,
      "calculating": false
    },
    "status": "confirmed",
    "payment_status": "paid",
    "createdAt": "2025-12-10T03:27:15.197000",
    "id": "5b47fc27-de48-42d5-a70d-8e226a895552",
    "referenceNumber": null
  },
  {
    "serviceType": "airport-shuttle",
    "pickupAddress": "43 Bright Street, Eden Terrace, Auckland 1021, New Zealand",
    "pickupAddresses": [],
    "dropoffAddress": "Auckland Airport, Auckland 2022, New Zealand",
    "date": "2025-12-20",
    "time": "10:30",
    "passengers": "5",
    "departureFlightNumber": "JQ115",
    "departureTime": "15:00",
    "arrivalFlightNumber": "",
    "arrivalTime": "",
    "name": "Robert Travis",
    "email": "robert.p.travis@icloud.com",
    "phone": "272369694",
    "notes": "Hi, guys! We've used you before. We are 2 parents and 3 kids (ages 16, 11, 11) and we will each have a carry-on and one suitcase to check.",
    "pricing": {
      "distance": 49.92,
      "basePrice": 124.8,
      "airportFee": 0,
      "oversizedLuggageFee": 0,
      "passengerFee": 40,
      "totalPrice": 200,
      "calculating": false
    },
    "status": "confirmed",
    "payment_status": "paid",
    "createdAt": "2025-12-09T22:46:39.753000",
    "id": "e59afd4e-3c1c-4ffa-9f2c-01675da70353",
    "referenceNumber": null
  },
  {
    "serviceType": "airport-shuttle",
    "pickupAddress": "7 welland place, hillcrest, auckland",
    "pickupAddresses": [],
    "dropoffAddress": "auckland international airport",
    "date": "2026-10-03",
    "time": "17:30",
    "passengers": "4",
    "departureFlightNumber": "",
    "departureTime": "20:30",
    "arrivalFlightNumber": "",
    "arrivalTime": "",
    "name": "Nicki Nicol",
    "email": "nickiball@gmail.com",
    "phone": "+64278197627",
    "notes": "",
    "pricing": {
      "distance": 69.68,
      "basePrice": 174.2,
      "airportFee": 0,
      "oversizedLuggageFee": 0,
      "passengerFee": 30,
      "totalPrice": 204.2,
      "calculating": false
    },
    "status": "pending",
    "payment_status": "pending",
    "createdAt": "2025-12-09T09:34:36.044000",
    "id": "57842e07-ea67-40d0-a9de-95fafcbc30a2",
    "referenceNumber": null
  },
  {
    "serviceType": "private-transfer",
    "pickupAddress": "1362 Whangaparaoa Road",
    "pickupAddresses": [],
    "dropoffAddress": "sculpteurium",
    "date": "2025-12-14",
    "time": "11:30",
    "passengers": "9",
    "departureFlightNumber": "",
    "departureTime": "",
    "arrivalFlightNumber": "",
    "arrivalTime": "",
    "name": "jill ryan",
    "email": "jill@youmanly.co.nz",
    "phone": "0272208506",
    "notes": "Can we pick up on way",
    "pricing": {
      "distance": 111,
      "basePrice": 277.5,
      "airportFee": 0,
      "oversizedLuggageFee": 0,
      "passengerFee": 80,
      "totalPrice": 357.5,
      "calculating": false
    },
    "status": "pending",
    "payment_status": "pending",
    "createdAt": "2025-12-09T00:33:50.604000",
    "id": "ba3d58ba-22dd-4ede-869c-718522a09c53",
    "referenceNumber": null
  },
  {
    "serviceType": "airport-shuttle",
    "pickupAddress": "73 Ridgedale Road",
    "pickupAddresses": [],
    "dropoffAddress": "Auckland Airport International ",
    "date": "2025-12-13",
    "time": "11:00",
    "passengers": "4",
    "departureFlightNumber": "",
    "departureTime": "",
    "arrivalFlightNumber": "",
    "arrivalTime": "",
    "name": "Savannah Sims",
    "email": "savannah.sims@icloud.com",
    "phone": "+642904503680",
    "notes": "4 people, 4 large suitcases",
    "pricing": {
      "distance": 54.89,
      "basePrice": 137.22,
      "airportFee": 0,
      "oversizedLuggageFee": 25,
      "passengerFee": 15,
      "totalPrice": 177.22,
      "calculating": false
    },
    "status": "confirmed",
    "payment_status": "paid",
    "createdAt": "2025-12-08T23:17:51.838000",
    "id": "f1e56351-a231-46a2-bd20-1e8c64f23e98",
    "referenceNumber": null
  },
  {
    "serviceType": "airport-shuttle",
    "pickupAddress": "73 Ridgedale Road",
    "pickupAddresses": [],
    "dropoffAddress": "International Terminal Auckland Airport",
    "date": "2025-12-13",
    "time": "11:00",
    "passengers": "4",
    "departureFlightNumber": "",
    "departureTime": "",
    "arrivalFlightNumber": "",
    "arrivalTime": "",
    "name": "Savannah Sims",
    "email": "savannah.sims@icloud.com",
    "phone": "+642904503680",
    "notes": "",
    "pricing": {
      "distance": 55.58,
      "basePrice": 138.95,
      "airportFee": 0,
      "oversizedLuggageFee": 25,
      "passengerFee": 15,
      "totalPrice": 178.95,
      "calculating": false
    },
    "status": "pending",
    "payment_status": "pending",
    "createdAt": "2025-12-08T23:14:21.900000",
    "id": "7589e91f-0de9-44b9-b0aa-dd5f04da2b99",
    "referenceNumber": null
  },
  {
    "serviceType": "private-transfer",
    "pickupAddress": "International Terminal, Auckland 2022, New Zealand",
    "pickupAddresses": [],
    "dropoffAddress": "8 Customs Street East, Auckland Central, Auckland 1010, New Zealand",
    "date": "2025-12-27",
    "time": "21:20",
    "passengers": "6",
    "departureFlightNumber": "",
    "departureTime": "",
    "arrivalFlightNumber": "",
    "arrivalTime": "",
    "name": "Yeri Kim",
    "email": "yeri.kim@outlook.com",
    "phone": "021538265",
    "notes": "Can you provide baby car seat? ",
    "pricing": {
      "distance": 21.8,
      "basePrice": 54.5,
      "airportFee": 0,
      "oversizedLuggageFee": 0,
      "passengerFee": 25,
      "totalPrice": 100,
      "calculating": false
    },
    "status": "pending",
    "payment_status": "pending",
    "createdAt": "2025-12-08T21:10:08.887000",
    "id": "698e91ef-c8be-424a-a712-9f00082bb4a3",
    "referenceNumber": null
  },
  {
    "serviceType": "airport-shuttle",
    "pickupAddress": "14 Ta Moko Drive, Gulf Harbour, Whangapar\u0101oa 0930, New Zealand",
    "pickupAddresses": [],
    "dropoffAddress": "Auckland Airport, International Terminal, Auckland Airport, Auckland 2022, New Zealand",
    "date": "2025-12-17",
    "time": "11:45",
    "passengers": "4",
    "departureFlightNumber": "",
    "departureTime": "",
    "arrivalFlightNumber": "",
    "arrivalTime": "",
    "name": "Maria Theresa Mendoza",
    "email": "aisahbautista@yahoo.com",
    "phone": "+64273818092",
    "notes": "4 checked-in luggage & 4 carry-on luggage. Thanks",
    "pricing": {
      "distance": 72.74,
      "basePrice": 181.85,
      "airportFee": 0,
      "oversizedLuggageFee": 0,
      "passengerFee": 15,
      "totalPrice": 196.85,
      "calculating": false
    },
    "status": "confirmed",
    "payment_status": "paid",
    "createdAt": "2025-12-08T05:00:25.127000",
    "id": "348696eb-db7e-4aae-af96-814330770c3d",
    "referenceNumber": null
  },
  {
    "serviceType": "airport-shuttle",
    "pickupAddress": "14 Ta Moko Drive, Gulf Harbour, Whangapar\u0101oa 0930, New Zealand",
    "pickupAddresses": [],
    "dropoffAddress": "Auckland Airport, International Terminal, Auckland Airport, Auckland 2022, New Zealand",
    "date": "2025-12-17",
    "time": "11:45",
    "passengers": "4",
    "departureFlightNumber": "QF3",
    "departureTime": "16:55",
    "arrivalFlightNumber": "",
    "arrivalTime": "14:05",
    "name": "Maria Theresa Mendoza",
    "email": "aisahbautista@yahoo.com",
    "phone": "+64273818092",
    "notes": "4 checked in luggage & carry-on luggage",
    "pricing": {
      "distance": 145.48,
      "basePrice": 363.7,
      "airportFee": 0,
      "oversizedLuggageFee": 0,
      "passengerFee": 30,
      "totalPrice": 330,
      "calculating": false,
      "overridden": true
    },
    "status": "confirmed",
    "payment_status": "pending",
    "createdAt": "2025-12-07T19:37:51.777000",
    "id": "cf3cb96a-633f-4a58-803b-eebe6231444d",
    "referenceNumber": null
  },
  {
    "serviceType": "airport-shuttle",
    "pickupAddress": "44A Ferry Road, Wade Heads, Whangapar\u0101oa 0932, New Zealand",
    "pickupAddresses": [],
    "dropoffAddress": "Auckland International Airport Ray Emery Drive, M\u0101ngere, Auckland 2022, New Zealand",
    "date": "2025-12-08",
    "time": "11:00",
    "passengers": "2",
    "departureFlightNumber": "JQ 115",
    "departureTime": "15:10",
    "arrivalFlightNumber": "",
    "arrivalTime": "",
    "name": "Ella Lins",
    "email": "ella.m.lins@gmail.com",
    "phone": "+642902624787",
    "notes": "Please note that the driveway is off Ferry Rd, it is a very long driveway travel all the way to the top. The house is on the right hand side. There is room to turn at the top.",
    "pricing": {
      "distance": 66.11,
      "basePrice": 165.28,
      "airportFee": 0,
      "oversizedLuggageFee": 0,
      "passengerFee": 5,
      "totalPrice": 170.28,
      "calculating": false
    },
    "status": "confirmed",
    "payment_status": "paid",
    "createdAt": "2025-12-07T08:40:06.453000",
    "id": "f68ec46e-9704-4f90-92c6-6ce0d1f5cd5d",
    "referenceNumber": null
  },
  {
    "serviceType": "airport-shuttle",
    "pickupAddress": "82 Manuel Road, Silverdale 0932, New Zealand",
    "pickupAddresses": [],
    "dropoffAddress": "International Terminal, Auckland 2022, New Zealand",
    "date": "2025-12-25",
    "time": "16:00",
    "passengers": "5",
    "departureFlightNumber": "NZ24",
    "departureTime": "20:30",
    "arrivalFlightNumber": "",
    "arrivalTime": "",
    "name": "Phil O'Connell",
    "email": "phillip.oconnell@xtra.co.nz",
    "phone": "+6421300518",
    "notes": "",
    "pricing": {
      "distance": 118.26,
      "basePrice": 295.66,
      "airportFee": 0,
      "oversizedLuggageFee": 50,
      "passengerFee": 40,
      "totalPrice": 385.66,
      "calculating": false
    },
    "status": "confirmed",
    "payment_status": "paid",
    "createdAt": "2025-12-07T08:05:45.893000",
    "id": "f95140e5-3107-4113-a181-7b91dba6f189",
    "referenceNumber": null
  },
  {
    "serviceType": "airport-shuttle",
    "pickupAddress": "49 Belmont Terrace, Milford, Auckland 0620, New Zealand",
    "pickupAddresses": [],
    "dropoffAddress": "Auckland International Airport Ray Emery Drive, M\u0101ngere, Auckland 2022, New Zealand",
    "date": "2025-12-19",
    "time": "07:15",
    "passengers": "5",
    "departureFlightNumber": "Nz284",
    "departureTime": "11:20",
    "arrivalFlightNumber": "",
    "arrivalTime": "",
    "name": "Jasmine Sim",
    "email": "jasmineclsim@gmail.com",
    "phone": "021776606",
    "notes": "2 large luggages, 2 standard size",
    "pricing": {
      "distance": 37.99,
      "basePrice": 94.98,
      "airportFee": 0,
      "oversizedLuggageFee": 0,
      "passengerFee": 20,
      "totalPrice": 114.98,
      "calculating": false
    },
    "status": "confirmed",
    "payment_status": "paid",
    "createdAt": "2025-12-07T06:09:33.993000",
    "id": "ef82e25f-0661-4249-95d0-6c29cb571684",
    "referenceNumber": null
  }
]